Metadata-Version: 1.1
Name: sphinxstl
Version: 0.1.0
Summary: An extension to visualize STL files in your Sphinx documentation
Home-page: https://github.com/Peque/sphinxstl
Author: Miguel Sánchez de León Peque
Author-email: peque@neosit.es
License: BSD License
Platform: UNKNOWN
Classifier: Development Status :: 4 - Beta
Classifier: Intended Audience :: Developers
Classifier: Topic :: Documentation
Classifier: Topic :: Software Development
Classifier: Topic :: Utilities
Classifier: License :: OSI Approved :: BSD License
Classifier: Operating System :: OS Independent
Classifier: Programming Language :: Python :: 3
Classifier: Framework :: Sphinx :: Extension
